isostream/__init__.py
isostream/client.py
isostream/utils.py
isostream-1.1.0.dist-info/LICENSE
isostream-1.1.0.dist-info/METADATA
isostream-1.1.0.dist-info/WHEEL
isostream-1.1.0.dist-info/top_level.txt
isostream-1.1.0.dist-info/RECORD
