Metadata-Version: 2.1
Name: isostream
Version: 1.1.0
Summary: Python Client for the IsoStream API
Home-page: https://github.com/dftrading/isostream
Author: IsoStream
Author-email: info@isostream.io
License: MIT
License-File: LICENSE
Requires-Dist: pandas
Requires-Dist: requests
